LICENSE
MANIFEST.in
README.rst
setup.py
gax_google_cloud_vision_v1.egg-info/PKG-INFO
gax_google_cloud_vision_v1.egg-info/SOURCES.txt
gax_google_cloud_vision_v1.egg-info/dependency_links.txt
gax_google_cloud_vision_v1.egg-info/namespace_packages.txt
gax_google_cloud_vision_v1.egg-info/requires.txt
gax_google_cloud_vision_v1.egg-info/top_level.txt
google/__init__.py
google/__init__.pyc
google/cloud/__init__.py
google/cloud/__init__.pyc
google/cloud/vision/__init__.py
google/cloud/vision/v1/__init__.py
google/cloud/vision/v1/image_annotator_api.py
google/cloud/vision/v1/image_annotator_client_config.json